vadtk/__init__.py
vadtk/utils.py
vadtk/tests/__init__.py
vadtk/tests/test_class_audio.py
vadtk-0.0.4.dist-info/DESCRIPTION.rst
vadtk-0.0.4.dist-info/METADATA
vadtk-0.0.4.dist-info/RECORD
vadtk-0.0.4.dist-info/WHEEL
vadtk-0.0.4.dist-info/metadata.json
vadtk-0.0.4.dist-info/top_level.txt
