Metadata-Version: 2.0
Name: vadtk
Version: 0.0.4
Summary: A toy voice activity detection tool kit
Home-page: https://github.com/hebinhao1993/VADTK
Author: hebinhao1993
Author-email: hebinhao1993@outlook.com
License: UNKNOWN
Keywords: toy voice activity detection tool kit
Platform: UNKNOWN
Classifier: Development Status :: 3 - Alpha
Classifier: Intended Audience :: Developers
Classifier: License :: OSI Approved :: MIT License
Classifier: Programming Language :: Python :: 3
Classifier: Programming Language :: Python :: 3.5
Requires-Dist: numpy
Requires-Dist: scipy
Requires-Dist: resampy
